odoo/addons/shopinvader_api_customer/README.rst
odoo/addons/shopinvader_api_customer/__init__.py
odoo/addons/shopinvader_api_customer/__manifest__.py
odoo/addons/shopinvader_api_customer/i18n/shopinvader_api_customer.pot
odoo/addons/shopinvader_api_customer/readme/CONTRIBUTORS.rst
odoo/addons/shopinvader_api_customer/readme/DESCRIPTION.rst
odoo/addons/shopinvader_api_customer/routers/__init__.py
odoo/addons/shopinvader_api_customer/routers/customer.py
odoo/addons/shopinvader_api_customer/schemas/__init__.py
odoo/addons/shopinvader_api_customer/schemas/customer.py
odoo/addons/shopinvader_api_customer/static/description/icon.png
odoo/addons/shopinvader_api_customer/static/description/index.html
odoo/addons/shopinvader_api_customer/tests/__init__.py
odoo/addons/shopinvader_api_customer/tests/test_shopinvader_customer_api.py
odoo_addon_shopinvader_api_customer-16.0.1.1.0.dist-info/METADATA
odoo_addon_shopinvader_api_customer-16.0.1.1.0.dist-info/WHEEL
odoo_addon_shopinvader_api_customer-16.0.1.1.0.dist-info/top_level.txt
odoo_addon_shopinvader_api_customer-16.0.1.1.0.dist-info/RECORD
