Metadata-Version: 2.1
Name: odoo-addon-shopinvader_api_customer
Version: 16.0.1.1.0
Summary: Adds service to manage shopinvader customer
Home-page: https://github.com/shopinvader/odoo-shopinvader
Author: ACSONE SA/NV,Odoo Community Association (OCA),Odoo Community Association (OCA)
Author-email: support@odoo-community.org
License: AGPL-3
Classifier: Programming Language :: Python
Classifier: Framework :: Odoo
Classifier: Framework :: Odoo :: 16.0
Classifier: License :: OSI Approved :: GNU Affero General Public License v3
Requires-Python: >=3.10
Requires-Dist: odoo-addon-extendable-fastapi<16.1dev,>=16.0dev
Requires-Dist: odoo-addon-fastapi<16.1dev,>=16.0dev
Requires-Dist: odoo<16.1dev,>=16.0a
